dotpptx/__init__.py
dotpptx/__main__.py
dotpptx/dotpptx.py
dotpptx/py.typed
dotpptx-0.1.2.dist-info/WHEEL
dotpptx-0.1.2.dist-info/entry_points.txt
dotpptx-0.1.2.dist-info/METADATA
dotpptx-0.1.2.dist-info/RECORD
