Metadata-Version: 2.4
Name: dotpptx
Version: 0.1.2
Summary: dotpptx is a tool to convert PowerPoint files to XML and back.
Author: Antonio Feregrino
Author-email: Antonio Feregrino <antonio.feregrino@gmail.com>
License-Expression: MIT
Requires-Dist: click>=8.2.1
Requires-Python: >=3.10
